InstructionMemory.v
module IM(
	clk,
	Halt,
	address,
	instruction_out
);
parameter DATA_WIDTH = 8;
parameter ADDRESS_WIDTH = 5;
parameter MEMORY_DEPTH = 32;

input wire clk, Halt;
input wire [ADDRESS_WIDTH-1:0] address;
output reg [DATA_WIDTH-1:0] instruction_out;

reg [DATA_WIDTH-1:0] instructions[MEMORY_DEPTH-1:0]; 
reg hltSignal;

initial begin
        $readmemb("./instruction.mem", instructions, 0, 31);
end

initial begin
	hltSignal = 1'b0;
end

always@(posedge clk) begin
	if(Halt == 1'b1)
		hltSignal = 1'b1;
end

always@(posedge clk) begin
	if(!hltSignal)
		instruction_out = instructions[address];
	else
		instruction_out = instruction_out;
end

endmodule

InstructionMemory_tb.v
module IM_tb;

reg clk, Halt;
reg [4:0] address;
wire [7:0] instruction_out;

IM u_IM(
	.clk(clk),
	.Halt(Halt),
	.address(address),
	.instruction_out(instruction_out)
);

initial begin
	$dumpfile("IM.vcd");
	$dumpvars(0, IM_tb);
end

// Clock generation
initial begin
	clk = 0;
	forever #25 clk = ~clk;
end

initial begin
        // Initialize signals
        address = 5'b00000;
	Halt = 1'b0;

        // Write operation
        #50;
        address = 5'b10001;   // Write to address 17
        // Read operation
        #100;
        address = 5'b10010;   // Read from address 17
        #50;
	Halt = 1'b1;
        // End simulation
	#70;
	address = 5'b10001;
        #2000;
        $finish;
end

endmodule

IM.vcd
$date
	Tue Feb  4 19:24:36 2025
$end
$version
	Icarus Verilog
$end
$timescale
	1s
$end
$scope module IM_tb $end
$var wire 8 ! instruction_out [7:0] $end
$var reg 1 " Halt $end
$var reg 5 # address [4:0] $end
$var reg 1 $ clk $end
$scope module u_IM $end
$var wire 1 " Halt $end
$var wire 5 % address [4:0] $end
$var wire 1 $ clk $end
$var parameter 32 & ADDRESS_WIDTH $end
$var parameter 32 ' DATA_WIDTH $end
$var parameter 32 ( MEMORY_DEPTH $end
$var reg 1 ) hltSignal $end
$var reg 8 * instruction_out [7:0] $end
$upscope $end
$upscope $end
$enddefinitions $end
$comment Show the parameter values. $end
$dumpall
b100000 (
b1000 '
b101 &
$end
#0
$dumpvars
bx *
0)
b0 %
0$
b0 #
0"
bx !
$end
#25
b11111110 !
b11111110 *
1$
#50
0$
b10001 #
b10001 %
#75
b100000 !
b100000 *
1$
#100
0$
#125
1$
#150
0$
b10010 #
b10010 %
#175
b11110100 !
b11110100 *
1$
#200
0$
1"
#225
1)
1$
#250
0$
#270
b10001 #
b10001 %
